srcsrv/__init__.py
srcsrv/__main__.py
srcsrv/indexer.py
srcsrv/pdb.py
srcsrv/plugins/__init__.py
srcsrv/plugins/bitbucket.py
srcsrv/plugins/codebase.py
srcsrv/plugins/github.py
srcsrv/plugins/gitlab.py
srcsrv/plugins/plugin.py
srcsrv/tools/__init__.py
srcsrv/tools/api.py
srcsrv/utils/__init__.py
srcsrv-1.2.15.dist-info/LICENSE
srcsrv-1.2.15.dist-info/METADATA
srcsrv-1.2.15.dist-info/WHEEL
srcsrv-1.2.15.dist-info/top_level.txt
srcsrv-1.2.15.dist-info/RECORD
