Metadata-Version: 2.1
Name: srcsrv
Version: 1.2.15
Summary: Source indexing package
Home-page: https://github.com/urielmann/srcsrv-public
Author: Uri Mann
Author-email: abba.mann@gmail.com
License: MIT
Classifier: Programming Language :: Python :: 3
Classifier: License :: OSI Approved :: MIT License
Classifier: Operating System :: Microsoft :: Windows
Classifier: Development Status :: 4 - Beta
Requires-Python: >=3.8
License-File: LICENSE
Requires-Dist: requests >=2
Requires-Dist: GitPython >=3
